<?xml version="1.0" encoding="ISO-8859-1"?>
<api name='libxml2-python'>
  <files>
    <file name='python'>
     <exports symbol='libxml_registerXPathFunction'/>
    </file>
  </files>
  <symbols>
    <function name='xmlRegisterXPathFunction' file='python'>
      <info>Register a Python written function to the XPath interpreter</info>
      <return type='int' info="1 in case of success, 0 or -1 in case of error"/>
      <arg name='ctx' type='xmlXPathContextPtr' info='the xpathContext'/>
      <arg name='name' type='xmlChar *' info='the function name'/>
      <arg name='ns_uri' type='xmlChar *' info='the namespace or NULL'/>
      <arg name='f' type='pythonObject' info='the python function'/>
    </function>
    <function name='xmlRegisterErrorHandler' file='python'>
      <info>Register a Python written function to for error reporting. The function is called back as f(ctx, error).</info>
      <return type='int' info="1 in case of success, 0 or -1 in case of error"/>
      <arg name='f' type='pythonObject' info='the python function'/>
      <arg name='ctx' type='pythonObject' info='a context for the callback'/>
    </function>
    <function name='xmlCreatePushParser' file='python'>
      <info>Create a progressive parser context to build either an event flow if the SAX object is not None, or a DOM tree otherwise.</info>
      <return type='xmlParserCtxtPtr' info="the parser context or None in case of error"/>
      <arg name='SAX' type='pythonObject' info='the SAX callback object or None'/>
      <arg name='chunk' type='xmlChar *' info='the initial data'/>
      <arg name='size' type='int' info='the size of the initial data'/>
      <arg name='URI' type='xmlChar *' info='The URI used for base computations'/>
    </function>
    <function name='xmlParserGetDoc' file='python_accessor'>
      <info>Get the document tree from a parser context.</info>
      <return type='xmlDocPtr' info="the document tree" field="myDoc"/>
      <arg name='ctxt' type='xmlParserCtxtPtr' info='the SAX callback object or None'/>
    </function>
  </symbols>
</api>
